postcode_eu_api_client/__init__.py
postcode_eu_api_client/client.py
postcode_eu_api_client/exceptions.py
postcode_eu_api_client/py.typed
postcode_eu_api_client-1.0.1.dist-info/WHEEL
postcode_eu_api_client-1.0.1.dist-info/METADATA
postcode_eu_api_client-1.0.1.dist-info/RECORD
