Metadata-Version: 2.4
Name: postcode-eu-api-client
Version: 1.0.1
Summary: Python client for the Postcode.eu API
Author: Postcode.eu
Author-email: Postcode.eu <tech@postcode.eu>
License-Expression: BSD-2-Clause
Requires-Dist: requests>=2.0,<3.0
Requires-Python: >=3.10
Project-URL: Homepage, https://www.postcode.eu/products/address-api
Project-URL: Issues, https://github.com/postcode-nl/postcode-eu-api-client-python/issues
Project-URL: Repository, https://github.com/postcode-nl/postcode-eu-api-client-python
